{
  "version": "7",
  "dialect": "postgresql",
  "entries": [
    {
      "idx": 0,
      "version": "7",
      "when": 1776127608879,
      "tag": "0000_supreme_dragon_man",
      "breakpoints": true
    },
    {
      "idx": 1,
      "version": "7",
      "when": 1776296034895,
      "tag": "0001_numerous_leopardon",
      "breakpoints": true
    },
    {
      "idx": 2,
      "version": "7",
      "when": 1776305340325,
      "tag": "0002_damp_santa_claus",
      "breakpoints": true
    },
    {
      "idx": 3,
      "version": "7",
      "when": 1776313210293,
      "tag": "0003_sour_vindicator",
      "breakpoints": true
    },
    {
      "idx": 4,
      "version": "7",
      "when": 1776393396155,
      "tag": "0004_tan_landau",
      "breakpoints": true
    },
    {
      "idx": 5,
      "version": "7",
      "when": 1776469660445,
      "tag": "0005_romantic_satana",
      "breakpoints": true
    },
    {
      "idx": 6,
      "version": "7",
      "when": 1776473609608,
      "tag": "0006_team_space",
      "breakpoints": true
    }
  ]
}